README
setup.py
FlowCheck.egg-info/PKG-INFO
FlowCheck.egg-info/SOURCES.txt
FlowCheck.egg-info/dependency_links.txt
FlowCheck.egg-info/entry_points.txt
FlowCheck.egg-info/top_level.txt
flow/__init__.py
flow/flower.py