Metadata-Version: 1.1
Name: FlowCheck
Version: 0.4
Summary: 在linux终端基于ip命令获取统计通过网卡的流量信息
Home-page: https://github.com/hellflame/flow_check
Author: hellflame
Author-email: hellflamedly@gmail.com
License: MIT
Keywords: quantity of flow,flow check,flow
Platform: Ubuntu
Classifier: Development Status :: 4 - Beta
Classifier: Environment :: Console
Classifier: License :: OSI Approved :: MIT License
Classifier: Operating System :: POSIX :: Linux
Classifier: Programming Language :: Python
Classifier: Programming Language :: Python :: 2.7
